onion/__init__.py
onion/core.py
onion/utils.py
oniondctw-1.6.0.dist-info/METADATA
oniondctw-1.6.0.dist-info/WHEEL
oniondctw-1.6.0.dist-info/top_level.txt
oniondctw-1.6.0.dist-info/RECORD
