Metadata-Version: 2.4
Name: oniondctw
Version: 1.6.0
Summary: 洋蔥工具包 🧅 收錄洋蔥的名言與趣味功能！
Author-email: "dev, dev" <skull@tw-yichen.net>
Project-URL: Homepage, https://github.com/dc2023tw/oniondctw
Classifier: Programming Language :: Python :: 3
Classifier: Operating System :: OS Independent
Requires-Python: >=3.9
Requires-Dist: requests
Requires-Dist: discord.py
